molecule_driver_azure/__init__.py
molecule_driver_azure/driver.py
molecule_driver_azure/cookiecutter/cookiecutter.json
molecule_driver_azure/cookiecutter/{{cookiecutter.molecule_directory}}/{{cookiecutter.scenario_name}}/README.md
molecule_driver_azure/cookiecutter/{{cookiecutter.molecule_directory}}/{{cookiecutter.scenario_name}}/converge.yml
molecule_driver_azure/cookiecutter/{{cookiecutter.molecule_directory}}/{{cookiecutter.scenario_name}}/create.yml
molecule_driver_azure/cookiecutter/{{cookiecutter.molecule_directory}}/{{cookiecutter.scenario_name}}/destroy.yml
molecule_driver_azure/cookiecutter/{{cookiecutter.molecule_directory}}/{{cookiecutter.scenario_name}}/molecule.yml
molecule_driver_azure/cookiecutter/{{cookiecutter.molecule_directory}}/{{cookiecutter.scenario_name}}/prepare.yml
molecule_driver_azure/cookiecutter/{{cookiecutter.molecule_directory}}/{{cookiecutter.scenario_name}}/requirements.yml
molecule_driver_azure/cookiecutter/{{cookiecutter.molecule_directory}}/{{cookiecutter.scenario_name}}/side_effect.yml
molecule_driver_azure/cookiecutter/{{cookiecutter.molecule_directory}}/{{cookiecutter.scenario_name}}/verify.yml
molecule_driver_azure/test/__init__.py
molecule_driver_azure/test/test_driver.py
molecule_driver_azure/test/functional/__init__.py
molecule_driver_azure/test/functional/conftest.py
molecule_driver_azure/test/functional/test_azure.py
molecule_driver_azure/test/scenarios/driver/azure/molecule/default/converge.yml
molecule_driver_azure/test/scenarios/driver/azure/molecule/default/molecule.yml
molecule_driver_azure/test/scenarios/driver/azure/molecule/default/tests/test_default.py
molecule_driver_azure/test/scenarios/driver/azure/molecule/multi-node/converge.yml
molecule_driver_azure/test/scenarios/driver/azure/molecule/multi-node/molecule.yml
molecule_driver_azure/test/scenarios/driver/azure/molecule/multi-node/prepare.yml
molecule_driver_azure/test/scenarios/driver/azure/molecule/multi-node/tests/__init__.py
molecule_driver_azure-0.0.4.dist-info/LICENSE
molecule_driver_azure-0.0.4.dist-info/METADATA
molecule_driver_azure-0.0.4.dist-info/WHEEL
molecule_driver_azure-0.0.4.dist-info/entry_points.txt
molecule_driver_azure-0.0.4.dist-info/top_level.txt
molecule_driver_azure-0.0.4.dist-info/RECORD
